ceilometermiddleware/__init__.py
ceilometermiddleware/swift.py
ceilometermiddleware/tests/__init__.py
ceilometermiddleware/tests/base.py
ceilometermiddleware/tests/test_swift.py
ceilometermiddleware/tests/data/list_projects.yaml
ceilometermiddleware-3.9.0.dist-info/AUTHORS
ceilometermiddleware-3.9.0.dist-info/LICENSE
ceilometermiddleware-3.9.0.dist-info/METADATA
ceilometermiddleware-3.9.0.dist-info/WHEEL
ceilometermiddleware-3.9.0.dist-info/entry_points.txt
ceilometermiddleware-3.9.0.dist-info/pbr.json
ceilometermiddleware-3.9.0.dist-info/top_level.txt
ceilometermiddleware-3.9.0.dist-info/RECORD
